dearrayer/__init__.py
dearrayer/models/__init__.py
dearrayer/models/tissue_microarray.py
dearrayer/models/tma_core.py
dearrayer/models/tma_grid.py
dearrayer/services/__init__.py
dearrayer/services/grid_detecting_service.py
dearrayer/services/line_fitter.py
dearrayer-0.1.0.dist-info/METADATA
dearrayer-0.1.0.dist-info/WHEEL
dearrayer-0.1.0.dist-info/licenses/LICENSE
dearrayer-0.1.0.dist-info/RECORD
