Metadata-Version: 2.4
Name: dearrayer
Version: 0.1.0
Summary: Python tool for automated dearraying of Tissue Microarrays (TMA)
Project-URL: Homepage, https://github.com/bozeklab/dearrayer
Project-URL: Documentation, https://github.com/bozeklab/dearrayer#readme
Project-URL: Repository, https://github.com/bozeklab/dearrayer.git
Project-URL: Issues, https://github.com/bozeklab/dearrayer/issues
Author-email: Antoni Moszyński <amoszyns@uni-koeln.de>
Maintainer-email: Antoni Moszyński <amoszyns@uni-koeln.de>
License: Copyright (C) 2025 University of Cologne
License-File: LICENSE
Keywords: TMA,bioimage,dearray,image analysis,microscopy,pathology,tissue microarray
Classifier: Development Status :: 4 - Beta
Classifier: Intended Audience :: Science/Research
Classifier: License :: OSI Approved :: GNU General Public License v3 (GPLv3)
Classifier: Operating System :: OS Independent
Classifier: Programming Language :: Python :: 3
Classifier: Programming Language :: Python :: 3.11
Classifier: Programming Language :: Python :: 3.12
Classifier: Programming Language :: Python :: 3.13
Classifier: Topic :: Scientific/Engineering :: Bio-Informatics
Classifier: Topic :: Scientific/Engineering :: Image Processing
Classifier: Topic :: Scientific/Engineering :: Medical Science Apps.
Requires-Python: >=3.11
Requires-Dist: matplotlib>=3.10.0
Requires-Dist: numpy>=2.0.0
Requires-Dist: opencv-python>=4.8.0
Requires-Dist: scikit-image>=0.22.0
Requires-Dist: scikit-learn>=1.3.0
Requires-Dist: scipy>=1.11.0
